[{"model": "goods.products", "pk": 1, "fields": {"name": "T-Shirt", "slug": "t-shirt", "description": "A white T-shirt is a classic wardrobe essential, offering comfort and versatility.", "image": "goods_images/dress1_pkHBGNn.jpg", "price": "100.00", "discount": "10.00", "quantity": 2, "category": 3}}, {"model": "goods.products", "pk": 2, "fields": {"name": "Ipad Case", "slug": "ipad-case", "description": "Introducing the sleek and functional iPad case, designed to provide both style and protection for your device.", "image": "goods_images/ipad-case2.jpg", "price": "100.00", "discount": "5.00", "quantity": 3, "category": 6}}, {"model": "goods.products", "pk": 3, "fields": {"name": "Girl's super bag", "slug": "girls-super-bag", "description": "The stylish and versatile bag designed to meet all your needs.", "image": "goods_images/bag-1.jpg", "price": "290.00", "discount": "30.00", "quantity": 5, "category": 5}}, {"model": "goods.products", "pk": 4, "fields": {"name": "\"Blush Blossom\" Pink Bag", "slug": "blush-blossom-pink-bag", "description": "Elevate your style with our chic pink bag,\r\n                                    a sophisticated accessory that adds a touch of glamour to any outfit.", "image": "goods_images/bag-3.jpg", "price": "230.00", "discount": "50.00", "quantity": 7, "category": 5}}, {"model": "goods.products", "pk": 5, "fields": {"name": "Shoes", "slug": "shoes", "description": "White Shoes for Girls:\r\nCrafted with care from pristine white materials, these shoes are pure elegance.", "image": "goods_images/shoes-1.jpg", "price": "49.00", "discount": "20.00", "quantity": 2, "category": 7}}, {"model": "goods.products", "pk": 6, "fields": {"name": "White bag", "slug": "white-bag", "description": "This chic accessory embodies sophistication and versatility.", "image": "goods_images/bag-2.jpg", "price": "100.00", "discount": "30.00", "quantity": 2, "category": 5}}, {"model": "goods.products", "pk": 7, "fields": {"name": "\"Swan Fluff\" - shoes", "slug": "swan-fluff-shoes", "description": "\"Swan Fluff\" - adorable little shoes for girls:\r\nThese delicate shoes boast an elegant design and an appealing look.", "image": "goods_images/shoes-2.jpg", "price": "90.00", "discount": "25.00", "quantity": 5, "category": 7}}, {"model": "goods.products", "pk": 8, "fields": {"name": "\"Crystal Clear\" Glasses", "slug": "crystal-clear-glasses", "description": "These stylish glasses are both chic and practical.", "image": "goods_images/glass1.jpg", "price": "200.00", "discount": "10.00", "quantity": 5, "category": 4}}, {"model": "goods.products", "pk": 9, "fields": {"name": "\"Pink Serenade\" Dress", "slug": "pink-serenade-dress", "description": "This enchanting dress is a symphony of elegance and charm.", "image": "goods_images/dress2.jpg", "price": "350.00", "discount": "15.00", "quantity": 5, "category": 3}}, {"model": "goods.products", "pk": 10, "fields": {"name": "Black-glass", "slug": "black-glass", "description": "These sophisticated glasses exude timeless style and versatility.", "image": "goods_images/glass2.jpg", "price": "40.00", "discount": "5.00", "quantity": 2, "category": 4}}, {"model": "goods.products", "pk": 11, "fields": {"name": "White-dress", "slug": "white-dress", "description": "This stunning white dress embodies elegance and grace.", "image": "goods_images/dress3.jpg", "price": "200.00", "discount": "20.00", "quantity": 12, "category": 3}}, {"model": "goods.products", "pk": 12, "fields": {"name": "Green phone case", "slug": "green-phone-case", "description": "Elevate your phone's style with our vibrant green case.", "image": "goods_images/ipad-case1.jpg", "price": "20.00", "discount": "0.00", "quantity": 4, "category": 6}}]